token_counter/__init__.py
token_counter/_version.py
token_counter/count_tokens.py
token_counter-0.1.5.dist-info/METADATA
token_counter-0.1.5.dist-info/WHEEL
token_counter-0.1.5.dist-info/top_level.txt
token_counter-0.1.5.dist-info/RECORD
