Metadata-Version: 2.1
Name: token-counter
Version: 0.1.5
Summary: A token counter for counting tokens of LLM inputs and outputs
Home-page: https://gitlab.com/labsoft-ai/token-and-cost-manager
Author: Momcilo Krunic
Author-email: momcilo.krunic@labsoft.ai
License: MIT
Platform: UNKNOWN
Classifier: Programming Language :: Python :: 3
Classifier: License :: OSI Approved :: MIT License
Classifier: Operating System :: OS Independent
Requires-Dist: tiktoken
